<?xml version="1.0" encoding="UTF-8"?>
<MetaDataObject xmlns="http://v8.1c.ru/8.3/MDClasses" xmlns:app="http://v8.1c.ru/8.2/managed-application/core" xmlns:cfg="http://v8.1c.ru/8.1/data/enterprise/current-config" xmlns:cmi="http://v8.1c.ru/8.2/managed-application/cmi" xmlns:ent="http://v8.1c.ru/8.1/data/enterprise" xmlns:lf="http://v8.1c.ru/8.2/managed-application/logform" xmlns:style="http://v8.1c.ru/8.1/data/ui/style" xmlns:sys="http://v8.1c.ru/8.1/data/ui/fonts/system" xmlns:v8="http://v8.1c.ru/8.1/data/core" xmlns:v8ui="http://v8.1c.ru/8.1/data/ui" xmlns:web="http://v8.1c.ru/8.1/data/ui/colors/web" xmlns:win="http://v8.1c.ru/8.1/data/ui/colors/windows" xmlns:xen="http://v8.1c.ru/8.3/xcf/enums" xmlns:xpr="http://v8.1c.ru/8.3/xcf/predef" xmlns:xr="http://v8.1c.ru/8.3/xcf/readable" xmlns:xs="http://www.w3.org/2001/XMLSchema" xmlns:xsi="http://www.w3.org/2001/XMLSchema-instance" version="2.18">
	<Constant uuid="2227c2a3-8309-4bd6-b1b9-bd4b4334ad82">
		<InternalInfo>
			<xr:GeneratedType name="ConstantManager.кб99_ВерсияКонфигурации" category="Manager">
				<xr:TypeId>6d45a282-977f-464f-90b8-56d24796436f</xr:TypeId>
				<xr:ValueId>6a969f68-c646-4120-8c3a-45a46dbf7766</xr:ValueId>
			</xr:GeneratedType>
			<xr:GeneratedType name="ConstantValueManager.кб99_ВерсияКонфигурации" category="ValueManager">
				<xr:TypeId>b794abaf-4c20-474c-81c2-ce3406e96c04</xr:TypeId>
				<xr:ValueId>9cdb481e-9287-49c0-9a12-2ba676c0512c</xr:ValueId>
			</xr:GeneratedType>
			<xr:GeneratedType name="ConstantValueKey.кб99_ВерсияКонфигурации" category="ValueKey">
				<xr:TypeId>98755c49-915d-4ba8-ae1b-a0f2a2c2fa42</xr:TypeId>
				<xr:ValueId>bd6d8f8f-382d-45e7-9cbf-0326958503f2</xr:ValueId>
			</xr:GeneratedType>
		</InternalInfo>
		<Properties>
			<Name>кб99_ВерсияКонфигурации</Name>
			<Synonym>
				<v8:item>
					<v8:lang>ru</v8:lang>
					<v8:content>Версия конфигурации</v8:content>
				</v8:item>
			</Synonym>
			<Comment/>
			<Type>
				<v8:Type>xs:decimal</v8:Type>
				<v8:NumberQualifiers>
					<v8:Digits>2</v8:Digits>
					<v8:FractionDigits>0</v8:FractionDigits>
					<v8:AllowedSign>Any</v8:AllowedSign>
				</v8:NumberQualifiers>
			</Type>
			<UseStandardCommands>false</UseStandardCommands>
			<DefaultForm/>
			<ExtendedPresentation/>
			<Explanation/>
			<PasswordMode>false</PasswordMode>
			<Format/>
			<EditFormat/>
			<ToolTip>
				<v8:item>
					<v8:lang>ru</v8:lang>
					<v8:content>Используется для определения модулей переопределения в зависимости от выбранного вида типовйо конфигурации</v8:content>
				</v8:item>
			</ToolTip>
			<MarkNegatives>false</MarkNegatives>
			<Mask/>
			<MultiLine>false</MultiLine>
			<ExtendedEdit>false</ExtendedEdit>
			<MinValue xsi:nil="true"/>
			<MaxValue xsi:nil="true"/>
			<FillChecking>DontCheck</FillChecking>
			<ChoiceFoldersAndItems>Items</ChoiceFoldersAndItems>
			<ChoiceParameterLinks/>
			<ChoiceParameters/>
			<QuickChoice>Auto</QuickChoice>
			<ChoiceForm/>
			<LinkByType/>
			<ChoiceHistoryOnInput>Auto</ChoiceHistoryOnInput>
			<DataLockControlMode>Managed</DataLockControlMode>
			<DataHistory>DontUse</DataHistory>
			<UpdateDataHistoryImmediatelyAfterWrite>false</UpdateDataHistoryImmediatelyAfterWrite>
			<ExecuteAfterWriteDataHistoryVersionProcessing>false</ExecuteAfterWriteDataHistoryVersionProcessing>
		</Properties>
	</Constant>
</MetaDataObject>